pytorrplay/__init__.py
pytorrplay/__main__.py
pytorrplay/arg_parser.py
pytorrplay/config_utils.py
pytorrplay/pytorr_play.py
pytorrplay/streamer.py
pytorrplay/ui_methods.py
pytorrplay-0.0.3.dist-info/METADATA
pytorrplay-0.0.3.dist-info/WHEEL
pytorrplay-0.0.3.dist-info/entry_points.txt
pytorrplay-0.0.3.dist-info/RECORD
