Metadata-Version: 2.1
Name: pytorrplay
Version: 0.0.3
Summary: Tool for streaming videos from torrrents
Home-page: https://gitlab.com/imithrellas/PyTorr-Play
License: MIT
Keywords: torrent,jackett,curses,rofi,mpv,media
Author: imithrellas
Requires-Python: >=3.10,<3.11
Classifier: License :: OSI Approved :: MIT License
Classifier: Programming Language :: Python :: 3
Classifier: Programming Language :: Python :: 3.10
Requires-Dist: Levenshtein (>=0.25.1,<0.26.0)
Requires-Dist: PyYAML (==6.0.1)
Requires-Dist: dbus-python (>=1.3.2,<2.0.0)
Requires-Dist: fuzzywuzzy (==0.18.0)
Requires-Dist: libtorrent (==2.0.9)
Requires-Dist: mpv (>=1.0.6,<2.0.0)
Requires-Dist: plyer (==2.1.0)
Requires-Dist: python-mpv (==1.0.6)
Requires-Dist: requests (==2.32.2)
Requires-Dist: tabulate (==0.9.0)
Project-URL: Repository, https://gitlab.com/imithrellas/PyTorr-Play
